[
  {
    "inputs": [],
    "stateMutability": "nonpayable",
    "type": "constructor"
  },
  {
    "anonymous": false,
    "inputs": [
      {
        "indexed": false,
        "internalType": "address",
        "name": "poodAddr",
        "type": "address"
      },
      {
        "indexed": false,
        "internalType": "address",
        "name": "beneficiary",
        "type": "address"
      },
      {
        "indexed": false,
        "internalType": "uint256",
        "name": "totalAmount",
        "type": "uint256"
      }
    ],
    "name": "BeneficiaryAdded",
    "type": "event"
  },
  {
    "anonymous": false,
    "inputs": [
      {
        "indexed": false,
        "internalType": "address",
        "name": "id",
        "type": "address"
      },
      {
        "components": [
          {
            "internalType": "string",
            "name": "vestingTerm",
            "type": "string"
          },
          {
            "internalType": "uint256",
            "name": "createdAt",
            "type": "uint256"
          },
          {
            "internalType": "address",
            "name": "poolAdmin",
            "type": "address"
          },
          {
            "internalType": "address",
            "name": "poolAddr",
            "type": "address"
          },
          {
            "internalType": "uint256",
            "name": "totalPoolCap",
            "type": "uint256"
          },
          {
            "internalType": "uint256",
            "name": "totalReleasedAmount",
            "type": "uint256"
          },
          {
            "internalType": "uint256",
            "name": "totalVestingAdded",
            "type": "uint256"
          }
        ],
        "indexed": false,
        "internalType": "struct IFactory.VestingPool",
        "name": "infos",
        "type": "tuple"
      }
    ],
    "name": "NewPool",
    "type": "event"
  },
  {
    "anonymous": false,
    "inputs": [
      {
        "indexed": false,
        "internalType": "address",
        "name": "poodAddr",
        "type": "address"
      }
    ],
    "name": "Paused",
    "type": "event"
  },
  {
    "anonymous": false,
    "inputs": [
      {
        "indexed": false,
        "internalType": "address",
        "name": "poodAddr",
        "type": "address"
      },
      {
        "indexed": false,
        "internalType": "uint256",
        "name": "newCap",
        "type": "uint256"
      }
    ],
    "name": "PoolCapUpdated",
    "type": "event"
  },
  {
    "anonymous": false,
    "inputs": [
      {
        "indexed": true,
        "internalType": "bytes32",
        "name": "role",
        "type": "bytes32"
      },
      {
        "indexed": true,
        "internalType": "bytes32",
        "name": "previousAdminRole",
        "type": "bytes32"
      },
      {
        "indexed": true,
        "internalType": "bytes32",
        "name": "newAdminRole",
        "type": "bytes32"
      }
    ],
    "name": "RoleAdminChanged",
    "type": "event"
  },
  {
    "anonymous": false,
    "inputs": [
      {
        "indexed": true,
        "internalType": "bytes32",
        "name": "role",
        "type": "bytes32"
      },
      {
        "indexed": true,
        "internalType": "address",
        "name": "account",
        "type": "address"
      },
      {
        "indexed": true,
        "internalType": "address",
        "name": "sender",
        "type": "address"
      }
    ],
    "name": "RoleGranted",
    "type": "event"
  },
  {
    "anonymous": false,
    "inputs": [
      {
        "indexed": true,
        "internalType": "bytes32",
        "name": "role",
        "type": "bytes32"
      },
      {
        "indexed": true,
        "internalType": "address",
        "name": "account",
        "type": "address"
      },
      {
        "indexed": true,
        "internalType": "address",
        "name": "sender",
        "type": "address"
      }
    ],
    "name": "RoleRevoked",
    "type": "event"
  },
  {
    "anonymous": false,
    "inputs": [
      {
        "indexed": false,
        "internalType": "address",
        "name": "poodAddr",
        "type": "address"
      }
    ],
    "name": "Unpaused",
    "type": "event"
  },
  {
    "anonymous": false,
    "inputs": [
      {
        "indexed": false,
        "internalType": "address",
        "name": "beneficiary",
        "type": "address"
      },
      {
        "indexed": false,
        "internalType": "uint256",
        "name": "amount",
        "type": "uint256"
      },
      {
        "indexed": false,
        "internalType": "address",
        "name": "poolAddr",
        "type": "address"
      }
    ],
    "name": "Withdrawn",
    "type": "event"
  },
  {
    "inputs": [],
    "name": "DEFAULT_ADMIN_ROLE",
    "outputs": [
      {
        "internalType": "bytes32",
        "name": "",
        "type": "bytes32"
      }
    ],
    "stateMutability": "view",
    "type": "function"
  },
  {
    "inputs": [],
    "name": "MASTER_POOL_ADMIN",
    "outputs": [
      {
        "internalType": "bytes32",
        "name": "",
        "type": "bytes32"
      }
    ],
    "stateMutability": "view",
    "type": "function"
  },
  {
    "inputs": [],
    "name": "POOL_ADMIN",
    "outputs": [
      {
        "internalType": "bytes32",
        "name": "",
        "type": "bytes32"
      }
    ],
    "stateMutability": "view",
    "type": "function"
  },
  {
    "inputs": [
      {
        "internalType": "address",
        "name": "_pooAddr",
        "type": "address"
      },
      {
        "internalType": "address[]",
        "name": "_beneficiaries",
        "type": "address[]"
      },
      {
        "internalType": "uint256[]",
        "name": "_totalAmountArr",
        "type": "uint256[]"
      }
    ],
    "name": "addBeneficiaries",
    "outputs": [],
    "stateMutability": "nonpayable",
    "type": "function"
  },
  {
    "inputs": [
      {
        "internalType": "address",
        "name": "_pooAddr",
        "type": "address"
      },
      {
        "internalType": "address",
        "name": "_beneficiary",
        "type": "address"
      },
      {
        "internalType": "uint256",
        "name": "_totalAmount",
        "type": "uint256"
      }
    ],
    "name": "addBeneficiary",
    "outputs": [],
    "stateMutability": "nonpayable",
    "type": "function"
  },
  {
    "inputs": [
      {
        "internalType": "address",
        "name": "_poolAddr",
        "type": "address"
      }
    ],
    "name": "getPoolDetails",
    "outputs": [
      {
        "components": [
          {
            "internalType": "string",
            "name": "vestingTerm",
            "type": "string"
          },
          {
            "internalType": "uint256",
            "name": "createdAt",
            "type": "uint256"
          },
          {
            "internalType": "address",
            "name": "poolAdmin",
            "type": "address"
          },
          {
            "internalType": "address",
            "name": "poolAddr",
            "type": "address"
          },
          {
            "internalType": "uint256",
            "name": "totalPoolCap",
            "type": "uint256"
          },
          {
            "internalType": "uint256",
            "name": "totalReleasedAmount",
            "type": "uint256"
          },
          {
            "internalType": "uint256",
            "name": "totalVestingAdded",
            "type": "uint256"
          }
        ],
        "internalType": "struct IFactory.VestingPool",
        "name": "",
        "type": "tuple"
      }
    ],
    "stateMutability": "view",
    "type": "function"
  },
  {
    "inputs": [],
    "name": "getPoolLength",
    "outputs": [
      {
        "internalType": "uint256",
        "name": "",
        "type": "uint256"
      }
    ],
    "stateMutability": "view",
    "type": "function"
  },
  {
    "inputs": [],
    "name": "getPoolsAddress",
    "outputs": [
      {
        "internalType": "address[]",
        "name": "",
        "type": "address[]"
      }
    ],
    "stateMutability": "view",
    "type": "function"
  },
  {
    "inputs": [
      {
        "internalType": "bytes32",
        "name": "role",
        "type": "bytes32"
      }
    ],
    "name": "getRoleAdmin",
    "outputs": [
      {
        "internalType": "bytes32",
        "name": "",
        "type": "bytes32"
      }
    ],
    "stateMutability": "view",
    "type": "function"
  },
  {
    "inputs": [
      {
        "internalType": "bytes32",
        "name": "role",
        "type": "bytes32"
      },
      {
        "internalType": "address",
        "name": "account",
        "type": "address"
      }
    ],
    "name": "grantRole",
    "outputs": [],
    "stateMutability": "nonpayable",
    "type": "function"
  },
  {
    "inputs": [
      {
        "internalType": "bytes32",
        "name": "role",
        "type": "bytes32"
      },
      {
        "internalType": "address",
        "name": "account",
        "type": "address"
      }
    ],
    "name": "hasRole",
    "outputs": [
      {
        "internalType": "bool",
        "name": "",
        "type": "bool"
      }
    ],
    "stateMutability": "view",
    "type": "function"
  },
  {
    "inputs": [
      {
        "internalType": "string",
        "name": "_term",
        "type": "string"
      },
      {
        "internalType": "address",
        "name": "_poolAdmin",
        "type": "address"
      },
      {
        "internalType": "uint256",
        "name": "_startTime",
        "type": "uint256"
      },
      {
        "internalType": "uint256",
        "name": "_firstUnlockPercentage",
        "type": "uint256"
      },
      {
        "internalType": "uint256",
        "name": "_lockDuration",
        "type": "uint256"
      },
      {
        "internalType": "uint256",
        "name": "_vestingDuration",
        "type": "uint256"
      },
      {
        "internalType": "uint256",
        "name": "_vestingPeriods",
        "type": "uint256"
      },
      {
        "internalType": "uint256",
        "name": "_totalPoolCap",
        "type": "uint256"
      }
    ],
    "name": "newPool",
    "outputs": [],
    "stateMutability": "nonpayable",
    "type": "function"
  },
  {
    "inputs": [
      {
        "internalType": "address",
        "name": "_poolAddress",
        "type": "address"
      }
    ],
    "name": "pausePool",
    "outputs": [],
    "stateMutability": "nonpayable",
    "type": "function"
  },
  {
    "inputs": [
      {
        "internalType": "bytes32",
        "name": "role",
        "type": "bytes32"
      },
      {
        "internalType": "address",
        "name": "account",
        "type": "address"
      }
    ],
    "name": "renounceRole",
    "outputs": [],
    "stateMutability": "nonpayable",
    "type": "function"
  },
  {
    "inputs": [
      {
        "internalType": "bytes32",
        "name": "role",
        "type": "bytes32"
      },
      {
        "internalType": "address",
        "name": "account",
        "type": "address"
      }
    ],
    "name": "revokeRole",
    "outputs": [],
    "stateMutability": "nonpayable",
    "type": "function"
  },
  {
    "inputs": [
      {
        "internalType": "address",
        "name": "_treasuryAddr",
        "type": "address"
      }
    ],
    "name": "setTreasury",
    "outputs": [],
    "stateMutability": "nonpayable",
    "type": "function"
  },
  {
    "inputs": [
      {
        "internalType": "bytes4",
        "name": "interfaceId",
        "type": "bytes4"
      }
    ],
    "name": "supportsInterface",
    "outputs": [
      {
        "internalType": "bool",
        "name": "",
        "type": "bool"
      }
    ],
    "stateMutability": "view",
    "type": "function"
  },
  {
    "inputs": [],
    "name": "totalReleasedAmount",
    "outputs": [
      {
        "internalType": "uint256",
        "name": "",
        "type": "uint256"
      }
    ],
    "stateMutability": "view",
    "type": "function"
  },
  {
    "inputs": [],
    "name": "totalVestingAdded",
    "outputs": [
      {
        "internalType": "uint256",
        "name": "",
        "type": "uint256"
      }
    ],
    "stateMutability": "view",
    "type": "function"
  },
  {
    "inputs": [],
    "name": "treasury",
    "outputs": [
      {
        "internalType": "address",
        "name": "",
        "type": "address"
      }
    ],
    "stateMutability": "view",
    "type": "function"
  },
  {
    "inputs": [
      {
        "internalType": "address",
        "name": "_poolAddress",
        "type": "address"
      }
    ],
    "name": "unpausePool",
    "outputs": [],
    "stateMutability": "nonpayable",
    "type": "function"
  },
  {
    "inputs": [
      {
        "internalType": "address",
        "name": "_poolAddress",
        "type": "address"
      },
      {
        "internalType": "uint256",
        "name": "_newCap",
        "type": "uint256"
      }
    ],
    "name": "updatePoolCap",
    "outputs": [],
    "stateMutability": "nonpayable",
    "type": "function"
  },
  {
    "inputs": [
      {
        "internalType": "address",
        "name": "_beneficiary",
        "type": "address"
      },
      {
        "internalType": "uint256",
        "name": "_amount",
        "type": "uint256"
      }
    ],
    "name": "widthdraw",
    "outputs": [],
    "stateMutability": "nonpayable",
    "type": "function"
  }
]
